epyk_studio/__init__.py
epyk_studio/core/Page.py
epyk_studio/core/__init__.py
epyk_studio/core/cli/Server.py
epyk_studio/core/cli/__init__.py
epyk_studio/core/cli/__main__.py
epyk_studio/core/cli/cli_pages.py
epyk_studio/core/html/HtmlClipboards.py
epyk_studio/core/html/HtmlDashboards.py
epyk_studio/core/html/__init__.py
epyk_studio/core/html/options/OptDashboards.py
epyk_studio/core/html/options/__init__.py
epyk_studio/core/js/__init__.py
epyk_studio/core/js/html/JsHtmlClipboard.py
epyk_studio/core/js/html/JsHtmlDashboard.py
epyk_studio/core/js/html/__init__.py
epyk_studio/interfaces/Interface.py
epyk_studio/interfaces/__init__.py
epyk_studio/interfaces/studio/CompStudioBlog.py
epyk_studio/interfaces/studio/CompStudioDashboard.py
epyk_studio/interfaces/studio/CompStudioEvent.py
epyk_studio/interfaces/studio/CompStudioNews.py
epyk_studio/interfaces/studio/CompStudioQuiz.py
epyk_studio/interfaces/studio/CompStudioShopping.py
epyk_studio/interfaces/studio/CompStudioVitrine.py
epyk_studio/interfaces/studio/__init__.py
epyk_studio/interfaces/studio/components/CompStudioButtons.py
epyk_studio/interfaces/studio/components/CompStudioChips.py
epyk_studio/interfaces/studio/components/CompStudioContainers.py
epyk_studio/interfaces/studio/components/__init__.py
epyk_studio/lang/__init__.py
epyk_studio/lang/eng.py
epyk_studio/lang/fr.py
epyk_studio/static/images/blog.PNG
epyk_studio/static/images/collaborative.PNG
epyk_studio/static/images/django-logo.png
epyk_studio/static/images/epyklogo.png
epyk_studio/static/images/epyklogo_whole_big.png
epyk_studio/static/images/fastapi-logo.png
epyk_studio/static/images/flask.jpg
epyk_studio/static/images/monitoring.PNG
epyk_studio/static/images/tornado.jpg
epyk_studio/static/lang/__init__.py
epyk_studio/static/lang/eng.py
epyk_studio/static/lang/fr.py
epyk_studio/static/pages/__init__.py
epyk_studio/static/pages/analytics.py
epyk_studio/static/pages/catalog.py
epyk_studio/static/pages/code_editor.py
epyk_studio-1.3.0.dist-info/LICENSE
epyk_studio-1.3.0.dist-info/METADATA
epyk_studio-1.3.0.dist-info/WHEEL
epyk_studio-1.3.0.dist-info/entry_points.txt
epyk_studio-1.3.0.dist-info/top_level.txt
epyk_studio-1.3.0.dist-info/RECORD
