Metadata-Version: 2.1
Name: epyk-studio
Version: 1.3.0
Summary: A simple way to create rich interactive websites from Python
Home-page: https://github.com/epykure/epyk-studio
Author: epykure
Author-email: smith.pyotr@gmail.com
License: UNKNOWN
Project-URL: Documentation, http://www.epyk-studio.com
Project-URL: Code, https://github.com/epykure/epyk-studio
Project-URL: Issue tracker, https://github.com/epykure/epyk-studio/issues
Platform: UNKNOWN
Classifier: Programming Language :: Python :: 3
Classifier: Programming Language :: Python :: 2.7
Classifier: License :: OSI Approved :: GNU General Public License (GPL)
Classifier: Operating System :: OS Independent
Classifier: Programming Language :: Python :: Implementation :: Jython
Classifier: Programming Language :: Python :: Implementation :: CPython
Classifier: Programming Language :: Python :: Implementation :: IronPython
Requires-Python: >=2.7
Requires-Dist: epyk
Requires-Dist: tornado
